[
	{
		"inputs": [
			{
				"internalType": "address",
				"name": "_systemToken",
				"type": "address"
			},
			{
				"internalType": "address",
				"name": "_selfToken",
				"type": "address"
			}
		],
		"stateMutability": "nonpayable",
		"type": "constructor"
	},
	{
		"anonymous": false,
		"inputs": [
			{
				"indexed": true,
				"internalType": "address",
				"name": "user",
				"type": "address"
			},
			{
				"indexed": false,
				"internalType": "uint256",
				"name": "systemAmount",
				"type": "uint256"
			},
			{
				"indexed": false,
				"internalType": "uint256",
				"name": "selfAmount",
				"type": "uint256"
			},
			{
				"indexed": false,
				"internalType": "string",
				"name": "productId",
				"type": "string"
			},
			{
				"indexed": false,
				"internalType": "uint256",
				"name": "timestamp",
				"type": "uint256"
			}
		],
		"name": "PurchaseArtifact",
		"type": "event"
	},
	{
		"inputs": [
			{
				"internalType": "uint256",
				"name": "systemAmount",
				"type": "uint256"
			},
			{
				"internalType": "uint256",
				"name": "selfAmount",
				"type": "uint256"
			},
			{
				"internalType": "string",
				"name": "productId",
				"type": "string"
			}
		],
		"name": "purchaseArtifact",
		"outputs": [],
		"stateMutability": "nonpayable",
		"type": "function"
	},
	{
		"inputs": [],
		"name": "selfToken",
		"outputs": [
			{
				"internalType": "contract IERC20",
				"name": "",
				"type": "address"
			}
		],
		"stateMutability": "view",
		"type": "function"
	},
	{
		"inputs": [],
		"name": "selfTokenBurnable",
		"outputs": [
			{
				"internalType": "contract ERC20Burnable",
				"name": "",
				"type": "address"
			}
		],
		"stateMutability": "view",
		"type": "function"
	},
	{
		"inputs": [],
		"name": "systemToken",
		"outputs": [
			{
				"internalType": "contract IERC20",
				"name": "",
				"type": "address"
			}
		],
		"stateMutability": "view",
		"type": "function"
	},
	{
		"inputs": [],
		"name": "systemTokenBurnable",
		"outputs": [
			{
				"internalType": "contract ERC20Burnable",
				"name": "",
				"type": "address"
			}
		],
		"stateMutability": "view",
		"type": "function"
	}
]